coshed_model/__init__.py
coshed_model/alarm_trespassing.py
coshed_model/alarmed.py
coshed_model/alarmed_notification_notification.py
coshed_model/alarmed_user_data.py
coshed_model/ansible_host_metadata.py
coshed_model/ansible_remote_identity.py
coshed_model/certificate.py
coshed_model/datetime_slots.py
coshed_model/documents.py
coshed_model/naming.py
coshed_model/poupin.py
coshed_model/roster.py
coshed_model/spof_client.py
coshed_model/tools.py
coshed_model-0.17.1.dist-info/METADATA
coshed_model-0.17.1.dist-info/WHEEL
coshed_model-0.17.1.dist-info/licenses/COPYING
coshed_model-0.17.1.dist-info/RECORD
