Metadata-Version: 2.4
Name: coshed-model
Version: 0.17.1
Author-email: doubleO8 <wb008@hdm-stuttgart.de>
License-Expression: GPL-2.0-only
License-File: COPYING
Requires-Python: >=3.9.2
Requires-Dist: boto3>=1.18.21
Requires-Dist: coshiota~=0.3.0
Requires-Dist: cryptography~=45.0.4
Requires-Dist: djali>=0.5.2
Requires-Dist: orjson~=3.10.18
Requires-Dist: pendulum!=3.0.0,>=2.1.2
Requires-Dist: pydantic~=1.10.13
Requires-Dist: sqlalchemy~=1.4.2
